syngular_ai/__init__.py
syngular_ai/content.py
syngular_ai/server.py
syngular_ai-0.2.0.dist-info/METADATA
syngular_ai-0.2.0.dist-info/WHEEL
syngular_ai-0.2.0.dist-info/RECORD
