Metadata-Version: 2.4
Name: syngular-ai
Version: 0.2.0
Summary: Syngular lets you connect to AI agents running locally or in production, stream their outputs, and collect structured feedback without infrastructure overhead.
Requires-Python: >=3.11
Requires-Dist: pydantic>=2.11.7
Requires-Dist: starlette>=0.47.1
Requires-Dist: twine>=6.1.0
Requires-Dist: uvicorn[standard]>=0.35.0
Requires-Dist: websocket>=0.2.1
